pycomposer/__init__.py
pycomposer/bar_gram.py
pycomposer/gan_composable.py
pycomposer/gan_composer.py
pycomposer/midi_controller.py
pycomposer/gancomposable/__init__.py
pycomposer/gancomposable/conditional_gan_composer.py
pycomposer/gancomposable/gan_composer.py
pycomposer/gancomposable/_mxnet/__init__.py
pycomposer/gancomposable/_mxnet/conditional_gan_composer.py
pycomposer/noisesampler/__init__.py
pycomposer/noisesampler/bar_gram_noise_sampler.py
pycomposer/noisesampler/bar_noise_sampler.py
pycomposer/noisesampler/midi_noise_sampler.py
pycomposer/samplabledata/__init__.py
pycomposer/samplabledata/noisesampler/__init__.py
pycomposer/samplabledata/noisesampler/bar_gram_noise_sampler.py
pycomposer/samplabledata/noisesampler/midi_noise_sampler.py
pycomposer/samplabledata/noisesampler/_mxnet/__init__.py
pycomposer/samplabledata/noisesampler/_mxnet/bar_gram_noise_sampler.py
pycomposer/samplabledata/noisesampler/_mxnet/midi_noise_sampler.py
pycomposer/samplabledata/truesampler/__init__.py
pycomposer/samplabledata/truesampler/bar_gram_true_sampler.py
pycomposer/samplabledata/truesampler/midi_true_sampler.py
pycomposer/samplabledata/truesampler/_mxnet/__init__.py
pycomposer/samplabledata/truesampler/_mxnet/bar_gram_true_sampler.py
pycomposer/samplabledata/truesampler/_mxnet/midi_true_sampler.py
pycomposer/samplabledata/truesampler/_mxnet/bargramtruesampler/__init__.py
pycomposer/samplabledata/truesampler/_mxnet/bargramtruesampler/conditonal_bar_gram_true_sampler.py
pycomposer/truesampler/__init__.py
pycomposer/truesampler/bar_gram_true_sampler.py
pycomposer/truesampler/bar_true_sampler.py
pycomposer/truesampler/midi_true_sampler.py
pycomposer-1.0.4.dist-info/METADATA
pycomposer-1.0.4.dist-info/RECORD
pycomposer-1.0.4.dist-info/WHEEL
pycomposer-1.0.4.dist-info/top_level.txt
