Metadata-Version: 2.1
Name: pycomposer
Version: 1.0.4
Summary: pycomposer is Python library for Algorithmic Composition or Automatic Composition based on the stochastic music theory and the Statistical machine learning problems. Especialy, this library provides apprication of the Algorithmic Composer based on Generative Adversarial Networks(GANs) and Conditional Generative Adversarial Networks(Conditional GANs).
Home-page: https://github.com/accel-brain/accel-brain-code/tree/master/Algorithmic-Composition
Author: accel-brain
Author-email: info@accel-brain.co.jp
License: GPL2
Keywords: GAN GANs MIDI Composition Generative Adversarial Networks Conditional MidiNet MuseGAN
Platform: UNKNOWN
Classifier: Development Status :: 5 - Production/Stable
Classifier: Intended Audience :: Information Technology
Classifier: Intended Audience :: Science/Research
Classifier: Topic :: Multimedia :: Sound/Audio :: MIDI
Classifier: Topic :: Scientific/Engineering :: Artificial Intelligence
Classifier: License :: OSI Approved :: GNU General Public License v2 (GPLv2)
Classifier: Programming Language :: Python :: 3
Requires-Dist: numpy
Requires-Dist: pandas
Requires-Dist: pretty-midi
Requires-Dist: pygan
Requires-Dist: accel-brain-base
